reflex_google_recaptcha_v2/__init__.py
reflex_google_recaptcha_v2/google_recaptcha_v2.py
reflex_google_recaptcha_v2-0.0.4.dist-info/METADATA
reflex_google_recaptcha_v2-0.0.4.dist-info/WHEEL
reflex_google_recaptcha_v2-0.0.4.dist-info/top_level.txt
reflex_google_recaptcha_v2-0.0.4.dist-info/RECORD
