Metadata-Version: 2.1
Name: reflex-google-recaptcha-v2
Version: 0.0.4
Summary: Google ReCAPTCHA v2 Integration
Author-email: Masen Furer <m_github@0x26.net>
License: Apache-2.0
Project-URL: Homepage, https://github.com/masenf/reflex-google-recaptcha-v2
Keywords: reflex,reflex-custom-components
Classifier: Development Status :: 4 - Beta
Requires-Python: >=3.8
Requires-Dist: httpx>=0.25.1
Requires-Dist: reflex>=0.4.6
Provides-Extra: dev
Requires-Dist: build; extra == "dev"
Requires-Dist: twine; extra == "dev"
